{"schrittCount":13,"vorgabenBlue":[{"text":"AH 06 „Projekt-Abschlussbericht“","hasLink":true,"link":""},{"text":"AH 03 „Bundesjugendförderung“","hasLink":true,"link":""}],"vorlagenBlue":[{"text":"","hasLink":false,"link":""}],"middleHead":"Projektabschluss u. -bericht d. JugendleiterIn","middleList":[{"text":"Rückgabe der Verantwortung an den Auftraggeber (Jugendvorstand)"},{"text":"Dank und Entlastung durch den Auftraggeber (Jugendvorstand)"}],"aufzeichnungOrange":[{"text":"AH 06 \"Projekt-Abschlussbericht\" (ausgefüllt)","hasLink":true,"link":""},{"text":"Bei BJF-Projekten: Projekt-Bericht mit Beilagen lt. AH 03 „Bundesjugendförderung“","hasLink":true,"link":""}],"verantwortlicherOrange":"ProjektleiterIn","informationOrange":"Jugendvorstand\nJugendreferentin KÖ;\nSachbearbeiterin BJF im Bundes­ verband ","orange":false}