{
  "schrittCount": 2,
  "vorgabenBlue": [
    { "text": "AH 01 \"Projektdefinition\"", "hasLink": true, "link": "" }
  ],
  "vorlagenBlue": [],
  "middleHead": "Vorlage / Besprechung",
  "middleList": [
    { "text": "im Rahmen des Vereinsvorstandes oder" },
    { "text": "im WIVO (je nach Thema) oder" },
    { "text": "in der Generalversammlung" }
  ],
  "aufzeichnungOrange": [
    {
      "text": "AH 01 \"Projektdefinition\" (ausgefüllte Vorlage)",
      "hasLink": true,
      "link": ""
    }
  ],
  "verantwortlicherOrange": "Vorstand, Wirtschaftsvorstand\noder eine „Sub-Gruppe“ (z.B. Kolpingjugend)\n",
  "informationOrange": "",
  "orange": false
}
